contextlogger.py
exceptions.py
contextlogger-1.0.1.dist-info/LICENSE.txt
contextlogger-1.0.1.dist-info/METADATA
contextlogger-1.0.1.dist-info/WHEEL
contextlogger-1.0.1.dist-info/top_level.txt
contextlogger-1.0.1.dist-info/RECORD
