Metadata-Version: 2.1
Name: contextlogger
Version: 1.0.1
Summary: A logging boilerplate enhanced by the use of contextvars
Home-page: https://github.com/kolitiri/contextlogger
Author: Christos Liontos
License: MIT
Project-URL: Source, https://github.com/kolitiri/contextlogger
Project-URL: Tracker, https://github.com/kolitiri/contextlogger/issues
Keywords: logging context
Platform: UNKNOWN
Classifier: Programming Language :: Python :: 3.7
Classifier: License :: OSI Approved :: MIT License
Classifier: Operating System :: OS Independent
Provides-Extra: dev
Requires-Dist: pytest (>=3.7) ; extra == 'dev'
